bioinfokit/__init__.py
bioinfokit/analys.py
bioinfokit/help.py
bioinfokit/visuz.py
bioinfokit-0.6.dist-info/LICENSE
bioinfokit-0.6.dist-info/METADATA
bioinfokit-0.6.dist-info/WHEEL
bioinfokit-0.6.dist-info/top_level.txt
bioinfokit-0.6.dist-info/RECORD
