Metadata-Version: 2.1
Name: bioinfokit
Version: 0.6
Summary: Bioinformatics data analysis and visualization toolkit
Home-page: http://reneshbedre.github.io/
Author: Renesh Bedre
Author-email: reneshbe@gmail.com
License: MIT
Platform: UNKNOWN
Classifier: Programming Language :: Python :: 3
Classifier: License :: OSI Approved :: MIT License
Classifier: Operating System :: Unix
Classifier: Operating System :: MacOS
Classifier: Operating System :: Microsoft :: Windows :: Windows 10
Classifier: Topic :: Scientific/Engineering :: Bio-Informatics
Classifier: Intended Audience :: Developers
Classifier: Intended Audience :: Education
Classifier: Intended Audience :: End Users/Desktop
Classifier: Intended Audience :: Science/Research
Requires-Dist: pandas
Requires-Dist: numpy
Requires-Dist: matplotlib
Requires-Dist: scipy
Requires-Dist: scikit-learn
Requires-Dist: seaborn
Requires-Dist: matplotlib-venn
Requires-Dist: tabulate
Requires-Dist: termcolor
Requires-Dist: statsmodels
Requires-Dist: textwrap3
